goes_api/__init__.py
goes_api/_version.py
goes_api/abi_area.py
goes_api/abi_pixel_time.py
goes_api/abi_utils.py
goes_api/alias.py
goes_api/checks.py
goes_api/configs.py
goes_api/download.py
goes_api/explore.py
goes_api/filter.py
goes_api/info.py
goes_api/io.py
goes_api/kerchunk.py
goes_api/listing.py
goes_api/operations.py
goes_api/query.py
goes_api/search.py
goes_api/data/ABI_Pixel_TimeOffset/goes-16_C_M3_1000.nc
goes_api/data/ABI_Pixel_TimeOffset/goes-16_C_M3_2000.nc
goes_api/data/ABI_Pixel_TimeOffset/goes-16_C_M3_500.nc
goes_api/data/ABI_Pixel_TimeOffset/goes-16_C_M6_1000.nc
goes_api/data/ABI_Pixel_TimeOffset/goes-16_C_M6_2000.nc
goes_api/data/ABI_Pixel_TimeOffset/goes-16_C_M6_500.nc
goes_api/data/ABI_Pixel_TimeOffset/goes-16_F_M3_1000.nc
goes_api/data/ABI_Pixel_TimeOffset/goes-16_F_M3_2000.nc
goes_api/data/ABI_Pixel_TimeOffset/goes-16_F_M3_500.nc
goes_api/data/ABI_Pixel_TimeOffset/goes-16_F_M4_1000.nc
goes_api/data/ABI_Pixel_TimeOffset/goes-16_F_M4_2000.nc
goes_api/data/ABI_Pixel_TimeOffset/goes-16_F_M4_500.nc
goes_api/data/ABI_Pixel_TimeOffset/goes-16_F_M6_1000.nc
goes_api/data/ABI_Pixel_TimeOffset/goes-16_F_M6_2000.nc
goes_api/data/ABI_Pixel_TimeOffset/goes-16_F_M6_500.nc
goes_api/data/ABI_Pixel_TimeOffset/goes-16_M_M3_1000.nc
goes_api/data/ABI_Pixel_TimeOffset/goes-16_M_M3_2000.nc
goes_api/data/ABI_Pixel_TimeOffset/goes-16_M_M3_500.nc
goes_api/data/ABI_Pixel_TimeOffset/goes-16_M_M6_1000.nc
goes_api/data/ABI_Pixel_TimeOffset/goes-16_M_M6_2000.nc
goes_api/data/ABI_Pixel_TimeOffset/goes-16_M_M6_500.nc
goes_api/data/ABI_Pixel_TimeOffset/goes-17_C_M6_1000.nc
goes_api/data/ABI_Pixel_TimeOffset/goes-17_C_M6_2000.nc
goes_api/data/ABI_Pixel_TimeOffset/goes-17_C_M6_500.nc
goes_api/data/ABI_Pixel_TimeOffset/goes-17_F_M3_1000.nc
goes_api/data/ABI_Pixel_TimeOffset/goes-17_F_M3_2000.nc
goes_api/data/ABI_Pixel_TimeOffset/goes-17_F_M3_500.nc
goes_api/data/ABI_Pixel_TimeOffset/goes-17_F_M4_1000.nc
goes_api/data/ABI_Pixel_TimeOffset/goes-17_F_M4_2000.nc
goes_api-0.1.8.dist-info/licenses/LICENSE
goes_api-0.1.8.dist-info/METADATA
goes_api-0.1.8.dist-info/WHEEL
goes_api-0.1.8.dist-info/top_level.txt
goes_api-0.1.8.dist-info/RECORD
