Metadata-Version: 2.4
Name: goes_api
Version: 0.1.8
Summary: Python API for downloading and searching GOES-16/17/18/19 satellite data on local and cloud storage.
Author-email: Gionata Ghiggi <gionata.ghiggi@epfl.ch>
License: MIT License
Project-URL: Homepage, https://github.com/ghiggi/goes_api
Project-URL: Source, https://github.com/ghiggi/goes_api
Project-URL: Tracker, https://github.com/ghiggi/goes_api/issues
Project-URL: Documentation, https://goes_api.readthedocs.io
Project-URL: changelog, https://github.com/ghigg/goes_api/CHANGELOG.md
Keywords: GOES-16,GOES-17,ABI,GLM,satellite,weather,meteorology,forecasting,EWS
Classifier: Development Status :: 2 - Pre-Alpha
Classifier: Intended Audience :: Science/Research
Classifier: Intended Audience :: Education
Classifier: License :: OSI Approved :: MIT License
Classifier: Natural Language :: English
Classifier: Operating System :: OS Independent
Classifier: Operating System :: Unix
Classifier: Operating System :: Microsoft
Classifier: Operating System :: MacOS
Classifier: Programming Language :: Python
Classifier: Programming Language :: Python :: 3
Classifier: Programming Language :: Python :: 3 :: Only
Classifier: Programming Language :: Python :: 3.7
Classifier: Programming Language :: Python :: 3.8
Classifier: Programming Language :: Python :: 3.9
Classifier: Programming Language :: Python :: 3.10
Classifier: Programming Language :: Python :: 3.11
Classifier: Topic :: Scientific/Engineering
Classifier: Topic :: Scientific/Engineering :: Atmospheric Science
Requires-Python: >=3.7
License-File: LICENSE
Requires-Dist: numpy
Requires-Dist: pandas
Requires-Dist: tqdm
Requires-Dist: trollsift
Requires-Dist: fsspec
Requires-Dist: s3fs
Requires-Dist: gcsfs
Provides-Extra: full
Requires-Dist: satpy; extra == "full"
Requires-Dist: xarray; extra == "full"
Requires-Dist: netcdf4; extra == "full"
Requires-Dist: kerchunk; extra == "full"
Requires-Dist: dask; extra == "full"
Requires-Dist: ujson; extra == "full"
Provides-Extra: dev
Requires-Dist: pre-commit; extra == "dev"
Requires-Dist: loghub; extra == "dev"
Requires-Dist: black[jupyter]; extra == "dev"
Requires-Dist: blackdoc; extra == "dev"
Requires-Dist: codespell; extra == "dev"
Requires-Dist: ruff; extra == "dev"
Requires-Dist: pytest; extra == "dev"
Requires-Dist: pytest-cov; extra == "dev"
Requires-Dist: pytest-mock; extra == "dev"
Requires-Dist: pytest-check; extra == "dev"
Requires-Dist: pytest-sugar; extra == "dev"
Requires-Dist: pytest-watcher; extra == "dev"
Requires-Dist: deepdiff; extra == "dev"
Requires-Dist: pip-tools; extra == "dev"
Requires-Dist: bumpver; extra == "dev"
Requires-Dist: twine; extra == "dev"
Requires-Dist: wheel; extra == "dev"
Requires-Dist: build; extra == "dev"
Requires-Dist: setuptools>=61.0.0; extra == "dev"
Requires-Dist: sphinx; extra == "dev"
Requires-Dist: sphinx-gallery; extra == "dev"
Requires-Dist: sphinx-book-theme; extra == "dev"
Requires-Dist: nbsphinx; extra == "dev"
Requires-Dist: sphinx_mdinclude; extra == "dev"
Dynamic: license-file
